message_room/__init__.py
message_room/generic_adaptive_card.j2
message_room/message_room.py
message_room/script.py
pywebexmessage-1.0.10.dist-info/entry_points.txt
pywebexmessage-1.0.10.dist-info/LICENSE
pywebexmessage-1.0.10.dist-info/WHEEL
pywebexmessage-1.0.10.dist-info/METADATA
pywebexmessage-1.0.10.dist-info/RECORD
