Metadata-Version: 2.1
Name: pywebexmessage
Version: 1.0.10
Summary: WebEx Bot that generates adaptive cards to a WebEx Room
Author: John Capobianco
Author-email: ptcapo@gmail.com
Requires-Python: >=3.8,<4.0
Classifier: Programming Language :: Python :: 3
Classifier: Programming Language :: Python :: 3.10
Classifier: Programming Language :: Python :: 3.8
Classifier: Programming Language :: Python :: 3.9
Requires-Dist: Jinja2 (>=3.1.2,<4.0.0)
Requires-Dist: requests (>=2.27.1,<3.0.0)
Requires-Dist: rich-click (>=1.3.0,<2.0.0)
